{"v":"5.5.2","fr":30,"w":24,"h":24,"nm":"Untitled","ddd":0,"assets":[],"layers":[{"hd":false,"ty":3,"ddd":0,"ind":0,"sr":1,"ao":0,"ks":{"o":{"a":0,"k":100},"r":{"a":0,"k":0},"p":{"a":0,"k":[12,12]},"a":{"a":0,"k":[0,0,0]},"s":{"a":0,"k":[100,100,100]},"sk":{"a":0,"k":0},"sa":{"a":0,"k":0}},"ip":0,"op":60,"st":0,"bm":0,"nm":"Fetch Loading","hasMask":false},{"hd":false,"ty":3,"ddd":0,"ind":1,"sr":1,"ao":0,"ks":{"o":{"a":0,"k":100},"r":{"a":0,"k":0},"p":{"a":0,"k":[0,0,0]},"a":{"a":0,"k":[0,0,0]},"s":{"a":0,"k":[100,100,100]},"sk":{"a":0,"k":0},"sa":{"a":0,"k":0}},"ip":0,"op":60,"st":0,"bm":0,"nm":"","parent":0,"hasMask":false},{"hd":false,"ty":3,"ddd":0,"ind":2,"sr":1,"ao":0,"ks":{"o":{"a":0,"k":100},"r":{"a":0,"k":0},"p":{"a":0,"k":[55.84062194824219,0.13518714904785156,0]},"a":{"a":0,"k":[0,0,0]},"s":{"a":0,"k":[40.00000059604645,40.00000059604645,100]},"sk":{"a":0,"k":0},"sa":{"a":0,"k":0}},"ip":0,"op":60,"st":0,"bm":0,"nm":"Fetch Loading Random","parent":1,"hasMask":false},{"hd":false,"ty":4,"ddd":0,"ind":3,"sr":1,"ao":0,"ks":{"o":{"a":1,"k":[{"i":{"x":[0],"y":[0]},"o":{"x":[1],"y":[1]},"h":1,"t":0,"s":[0]},{"i":{"x":[0],"y":[0]},"o":{"x":[1],"y":[1]},"h":1,"t":1,"s":[0]},{"i":{"x":[0],"y":[0]},"o":{"x":[1],"y":[1]},"h":1,"t":2,"s":[0]},{"i":{"x":[0],"y":[0]},"o":{"x":[1],"y":[1]},"h":1,"t":3,"s":[0]},{"i":{"x":[0],"y":[0]},"o":{"x":[1],"y":[1]},"h":1,"t":4,"s":[0]},{"i":{"x":[0],"y":[0]},"o":{"x":[1],"y":[1]},"h":1,"t":5,"s":[0]},{"i":{"x":[0],"y":[0]},"o":{"x":[1],"y":[1]},"h":1,"t":6,"s":[0]},{"i":{"x":[0],"y":[0]},"o":{"x":[1],"y":[1]},"h":1,"t":7,"s":[0]},{"i":{"x":[0],"y":[0]},"o":{"x":[1],"y":[1]},"h":1,"t":8,"s":[0.20421302444736467]},{"i":{"x":[0],"y":[0]},"o":{"x":[1],"y":[1]},"h":1,"t":9,"s":[0.8908846918708793]},{"i":{"x":[0],"y":[0]},"o":{"x":[1],"y":[1]},"h":1,"t":10,"s":[2.21322192707766]},{"i":{"x":[0],"y":[0]},"o":{"x":[1],"y":[1]},"h":1,"t":11,"s":[4.418489554435204]},{"i":{"x":[0],"y":[0]},"o":{"x":[1],"y":[1]},"h":1,"t":12,"s":[7.9490449733617154]},{"i":{"x":[0],"y":[0]},"o":{"x":[1],"y":[1]},"h":1,"t":13,"s":[13.733638806968115]},{"i":{"x":[0],"y":[0]},"o":{"x":[1],"y":[1]},"h":1,"t":14,"s":[24.35423892026852]},{"i":{"x":[0],"y":[0]},"o":{"x":[1],"y":[1]},"h":1,"t":15,"s":[50]},{"i":{"x":[0],"y":[0]},"o":{"x":[1],"y":[1]},"h":1,"t":16,"s":[75.64576107973147]},{"i":{"x":[0],"y":[0]},"o":{"x":[1],"y":[1]},"h":1,"t":17,"s":[86.2663611930319]},{"i":{"x":[0],"y":[0]},"o":{"x":[1],"y":[1]},"h":1,"t":18,"s":[92.05095502663828]},{"i":{"x":[0],"y":[0]},"o":{"x":[1],"y":[1]},"h":1,"t":19,"s":[95.5815104455648]},{"i":{"x":[0],"y":[0]},"o":{"x":[1],"y":[1]},"h":1,"t":20,"s":[97.78677807292233]},{"i":{"x":[0],"y":[0]},"o":{"x":[1],"y":[1]},"h":1,"t":21,"s":[99.10911530812913]},{"i":{"x":[0],"y":[0]},"o":{"x":[1],"y":[1]},"h":1,"t":22,"s":[99.79578697555264]},{"i":{"x":[0],"y":[0]},"o":{"x":[1],"y":[1]},"h":1,"t":23,"s":[100]},{"i":{"x":[0],"y":[0]},"o":{"x":[1],"y":[1]},"h":1,"t":24,"s":[100]},{"i":{"x":[0],"y":[0]},"o":{"x":[1],"y":[1]},"h":1,"t":25,"s":[100]},{"i":{"x":[0],"y":[0]},"o":{"x":[1],"y":[1]},"h":1,"t":26,"s":[100]},{"i":{"x":[0],"y":[0]},"o":{"x":[1],"y":[1]},"h":1,"t":27,"s":[100]},{"i":{"x":[0],"y":[0]},"o":{"x":[1],"y":[1]},"h":1,"t":28,"s":[100]},{"i":{"x":[0],"y":[0]},"o":{"x":[1],"y":[1]},"h":1,"t":29,"s":[100]},{"i":{"x":[0],"y":[0]},"o":{"x":[1],"y":[1]},"h":1,"t":30,"s":[100]},{"i":{"x":[0],"y":[0]},"o":{"x":[1],"y":[1]},"h":1,"t":31,"s":[100]},{"i":{"x":[0],"y":[0]},"o":{"x":[1],"y":[1]},"h":1,"t":32,"s":[100]},{"i":{"x":[0],"y":[0]},"o":{"x":[1],"y":[1]},"h":1,"t":33,"s":[100]},{"i":{"x":[0],"y":[0]},"o":{"x":[1],"y":[1]},"h":1,"t":34,"s":[100]},{"i":{"x":[0],"y":[0]},"o":{"x":[1],"y":[1]},"h":1,"t":35,"s":[100]},{"i":{"x":[0],"y":[0]},"o":{"x":[1],"y":[1]},"h":1,"t":36,"s":[99.81996951841349]},{"i":{"x":[0],"y":[0]},"o":{"x":[1],"y":[1]},"h":1,"t":37,"s":[99.21930195991678]},{"i":{"x":[0],"y":[0]},"o":{"x":[1],"y":[1]},"h":1,"t":38,"s":[98.07552789183043]},{"i":{"x":[0],"y":[0]},"o":{"x":[1],"y":[1]},"h":1,"t":39,"s":[96.1985180370635]},{"i":{"x":[0],"y":[0]},"o":{"x":[1],"y":[1]},"h":1,"t":40,"s":[93.26690563755626]},{"i":{"x":[0],"y":[0]},"o":{"x":[1],"y":[1]},"h":1,"t":41,"s":[88.6645929534551]},{"i":{"x":[0],"y":[0]},"o":{"x":[1],"y":[1]},"h":1,"t":42,"s":[80.94133940622638]},{"i":{"x":[0],"y":[0]},"o":{"x":[1],"y":[1]},"h":1,"t":43,"s":[65.18642797601737]},{"i":{"x":[0],"y":[0]},"o":{"x":[1],"y":[1]},"h":1,"t":44,"s":[34.81357202398262]},{"i":{"x":[0],"y":[0]},"o":{"x":[1],"y":[1]},"h":1,"t":45,"s":[19.05866059377366]},{"i":{"x":[0],"y":[0]},"o":{"x":[1],"y":[1]},"h":1,"t":46,"s":[11.335407046544887]},{"i":{"x":[0],"y":[0]},"o":{"x":[1],"y":[1]},"h":1,"t":47,"s":[6.733094362443737]},{"i":{"x":[0],"y":[0]},"o":{"x":[1],"y":[1]},"h":1,"t":48,"s":[3.8014819629364927]},{"i":{"x":[0],"y":[0]},"o":{"x":[1],"y":[1]},"h":1,"t":49,"s":[1.9244721081695615]},{"i":{"x":[0],"y":[0]},"o":{"x":[1],"y":[1]},"h":1,"t":50,"s":[0.7806980400832275]},{"i":{"x":[0],"y":[0]},"o":{"x":[1],"y":[1]},"h":1,"t":51,"s":[0.1800304815865128]},{"i":{"x":[0],"y":[0]},"o":{"x":[1],"y":[1]},"h":1,"t":52,"s":[0]},{"i":{"x":[0],"y":[0]},"o":{"x":[1],"y":[1]},"h":1,"t":53,"s":[0]},{"i":{"x":[0],"y":[0]},"o":{"x":[1],"y":[1]},"h":1,"t":54,"s":[0]},{"i":{"x":[0],"y":[0]},"o":{"x":[1],"y":[1]},"h":1,"t":55,"s":[0]},{"i":{"x":[0],"y":[0]},"o":{"x":[1],"y":[1]},"h":1,"t":56,"s":[0]},{"i":{"x":[0],"y":[0]},"o":{"x":[1],"y":[1]},"h":1,"t":57,"s":[0]},{"i":{"x":[0],"y":[0]},"o":{"x":[1],"y":[1]},"h":1,"t":58,"s":[0]},{"i":{"x":[0],"y":[0]},"o":{"x":[1],"y":[1]},"h":1,"t":59,"s":[0]}]},"r":{"a":0,"k":0},"p":{"a":0,"k":[-160.6298828125,-21.39166259765625,0]},"a":{"a":0,"k":[0,0,0]},"s":{"a":0,"k":[100,100,100]},"sk":{"a":0,"k":0},"sa":{"a":0,"k":0}},"shapes":[{"ty":"gr","it":[{"ty":"sh","ks":{"a":0,"k":{"c":true,"v":[[-5.8565793,-5.856579],[5.8565793,-5.856579],[5.8565793,5.856579],[-5.8565793,5.856579]],"i":[[0,0],[0,0],[0,0],[0,0]],"o":[[0,0],[0,0],[0,0],[0,0]]}}},{"ty":"fl","o":{"a":0,"k":100},"c":{"a":0,"k":[0.00392156862745098,0.054901960784313725,0.24313725490196078]}},{"ty":"rd","r":{"a":0,"k":0}},{"ty":"tr","o":{"a":0,"k":100},"r":{"a":0,"k":0},"p":{"a":0,"k":[0,0,0]},"a":{"a":0,"k":[0,0,0]},"s":{"a":0,"k":[100,100,100]}}]}],"ip":7,"op":60,"st":0,"bm":0,"nm":"Vector","parent":2,"hasMask":false},{"hd":false,"ty":4,"ddd":0,"ind":4,"sr":1,"ao":0,"ks":{"o":{"a":1,"k":[{"i":{"x":[0],"y":[0]},"o":{"x":[1],"y":[1]},"h":1,"t":0,"s":[0]},{"i":{"x":[0],"y":[0]},"o":{"x":[1],"y":[1]},"h":1,"t":1,"s":[0]},{"i":{"x":[0],"y":[0]},"o":{"x":[1],"y":[1]},"h":1,"t":2,"s":[0]},{"i":{"x":[0],"y":[0]},"o":{"x":[1],"y":[1]},"h":1,"t":3,"s":[0]},{"i":{"x":[0],"y":[0]},"o":{"x":[1],"y":[1]},"h":1,"t":4,"s":[0]},{"i":{"x":[0],"y":[0]},"o":{"x":[1],"y":[1]},"h":1,"t":5,"s":[0]},{"i":{"x":[0],"y":[0]},"o":{"x":[1],"y":[1]},"h":1,"t":6,"s":[0.20421302444736467]},{"i":{"x":[0],"y":[0]},"o":{"x":[1],"y":[1]},"h":1,"t":7,"s":[0.8908846918708793]},{"i":{"x":[0],"y":[0]},"o":{"x":[1],"y":[1]},"h":1,"t":8,"s":[2.21322192707766]},{"i":{"x":[0],"y":[0]},"o":{"x":[1],"y":[1]},"h":1,"t":9,"s":[4.418489554435204]},{"i":{"x":[0],"y":[0]},"o":{"x":[1],"y":[1]},"h":1,"t":10,"s":[7.9490449733617154]},{"i":{"x":[0],"y":[0]},"o":{"x":[1],"y":[1]},"h":1,"t":11,"s":[13.733638806968115]},{"i":{"x":[0],"y":[0]},"o":{"x":[1],"y":[1]},"h":1,"t":12,"s":[24.35423892026852]},{"i":{"x":[0],"y":[0]},"o":{"x":[1],"y":[1]},"h":1,"t":13,"s":[50]},{"i":{"x":[0],"y":[0]},"o":{"x":[1],"y":[1]},"h":1,"t":14,"s":[75.64576107973147]},{"i":{"x":[0],"y":[0]},"o":{"x":[1],"y":[1]},"h":1,"t":15,"s":[86.2663611930319]},{"i":{"x":[0],"y":[0]},"o":{"x":[1],"y":[1]},"h":1,"t":16,"s":[92.05095502663828]},{"i":{"x":[0],"y":[0]},"o":{"x":[1],"y":[1]},"h":1,"t":17,"s":[95.5815104455648]},{"i":{"x":[0],"y":[0]},"o":{"x":[1],"y":[1]},"h":1,"t":18,"s":[97.78677807292233]},{"i":{"x":[0],"y":[0]},"o":{"x":[1],"y":[1]},"h":1,"t":19,"s":[99.10911530812913]},{"i":{"x":[0],"y":[0]},"o":{"x":[1],"y":[1]},"h":1,"t":20,"s":[99.79578697555264]},{"i":{"x":[0],"y":[0]},"o":{"x":[1],"y":[1]},"h":1,"t":21,"s":[100]},{"i":{"x":[0],"y":[0]},"o":{"x":[1],"y":[1]},"h":1,"t":22,"s":[100]},{"i":{"x":[0],"y":[0]},"o":{"x":[1],"y":[1]},"h":1,"t":23,"s":[100]},{"i":{"x":[0],"y":[0]},"o":{"x":[1],"y":[1]},"h":1,"t":24,"s":[100]},{"i":{"x":[0],"y":[0]},"o":{"x":[1],"y":[1]},"h":1,"t":25,"s":[100]},{"i":{"x":[0],"y":[0]},"o":{"x":[1],"y":[1]},"h":1,"t":26,"s":[100]},{"i":{"x":[0],"y":[0]},"o":{"x":[1],"y":[1]},"h":1,"t":27,"s":[100]},{"i":{"x":[0],"y":[0]},"o":{"x":[1],"y":[1]},"h":1,"t":28,"s":[100]},{"i":{"x":[0],"y":[0]},"o":{"x":[1],"y":[1]},"h":1,"t":29,"s":[100]},{"i":{"x":[0],"y":[0]},"o":{"x":[1],"y":[1]},"h":1,"t":30,"s":[100]},{"i":{"x":[0],"y":[0]},"o":{"x":[1],"y":[1]},"h":1,"t":31,"s":[100]},{"i":{"x":[0],"y":[0]},"o":{"x":[1],"y":[1]},"h":1,"t":32,"s":[100]},{"i":{"x":[0],"y":[0]},"o":{"x":[1],"y":[1]},"h":1,"t":33,"s":[100]},{"i":{"x":[0],"y":[0]},"o":{"x":[1],"y":[1]},"h":1,"t":34,"s":[99.81996951841349]},{"i":{"x":[0],"y":[0]},"o":{"x":[1],"y":[1]},"h":1,"t":35,"s":[99.21930195991678]},{"i":{"x":[0],"y":[0]},"o":{"x":[1],"y":[1]},"h":1,"t":36,"s":[98.07552789183043]},{"i":{"x":[0],"y":[0]},"o":{"x":[1],"y":[1]},"h":1,"t":37,"s":[96.1985180370635]},{"i":{"x":[0],"y":[0]},"o":{"x":[1],"y":[1]},"h":1,"t":38,"s":[93.26690563755626]},{"i":{"x":[0],"y":[0]},"o":{"x":[1],"y":[1]},"h":1,"t":39,"s":[88.6645929534551]},{"i":{"x":[0],"y":[0]},"o":{"x":[1],"y":[1]},"h":1,"t":40,"s":[80.94133940622638]},{"i":{"x":[0],"y":[0]},"o":{"x":[1],"y":[1]},"h":1,"t":41,"s":[65.18642797601737]},{"i":{"x":[0],"y":[0]},"o":{"x":[1],"y":[1]},"h":1,"t":42,"s":[34.81357202398262]},{"i":{"x":[0],"y":[0]},"o":{"x":[1],"y":[1]},"h":1,"t":43,"s":[19.05866059377366]},{"i":{"x":[0],"y":[0]},"o":{"x":[1],"y":[1]},"h":1,"t":44,"s":[11.335407046544887]},{"i":{"x":[0],"y":[0]},"o":{"x":[1],"y":[1]},"h":1,"t":45,"s":[6.733094362443737]},{"i":{"x":[0],"y":[0]},"o":{"x":[1],"y":[1]},"h":1,"t":46,"s":[3.8014819629364927]},{"i":{"x":[0],"y":[0]},"o":{"x":[1],"y":[1]},"h":1,"t":47,"s":[1.9244721081695615]},{"i":{"x":[0],"y":[0]},"o":{"x":[1],"y":[1]},"h":1,"t":48,"s":[0.7806980400832275]},{"i":{"x":[0],"y":[0]},"o":{"x":[1],"y":[1]},"h":1,"t":49,"s":[0.1800304815865128]},{"i":{"x":[0],"y":[0]},"o":{"x":[1],"y":[1]},"h":1,"t":50,"s":[0]},{"i":{"x":[0],"y":[0]},"o":{"x":[1],"y":[1]},"h":1,"t":51,"s":[0]},{"i":{"x":[0],"y":[0]},"o":{"x":[1],"y":[1]},"h":1,"t":52,"s":[0]},{"i":{"x":[0],"y":[0]},"o":{"x":[1],"y":[1]},"h":1,"t":53,"s":[0]},{"i":{"x":[0],"y":[0]},"o":{"x":[1],"y":[1]},"h":1,"t":54,"s":[0]},{"i":{"x":[0],"y":[0]},"o":{"x":[1],"y":[1]},"h":1,"t":55,"s":[0]},{"i":{"x":[0],"y":[0]},"o":{"x":[1],"y":[1]},"h":1,"t":56,"s":[0]},{"i":{"x":[0],"y":[0]},"o":{"x":[1],"y":[1]},"h":1,"t":57,"s":[0]},{"i":{"x":[0],"y":[0]},"o":{"x":[1],"y":[1]},"h":1,"t":58,"s":[0]},{"i":{"x":[0],"y":[0]},"o":{"x":[1],"y":[1]},"h":1,"t":59,"s":[0]}]},"r":{"a":0,"k":0},"p":{"a":0,"k":[-160.95799255371094,-0.040069580078125,0]},"a":{"a":0,"k":[0,0,0]},"s":{"a":0,"k":[99.99999403953552,99.99999403953552,100]},"sk":{"a":0,"k":0},"sa":{"a":0,"k":0}},"shapes":[{"ty":"gr","it":[{"ty":"sh","ks":{"a":0,"k":{"c":true,"v":[[-5.5637503,-5.5637503],[5.5637503,-5.5637503],[5.5637503,5.5637503],[-5.5637503,5.5637503]],"i":[[0,0],[0,0],[0,0],[0,0]],"o":[[0,0],[0,0],[0,0],[0,0]]}}},{"ty":"fl","o":{"a":0,"k":100},"c":{"a":0,"k":[0.00392156862745098,0.054901960784313725,0.24313725490196078]}},{"ty":"rd","r":{"a":0,"k":0}},{"ty":"tr","o":{"a":0,"k":100},"r":{"a":0,"k":0},"p":{"a":0,"k":[0,0,0]},"a":{"a":0,"k":[0,0,0]},"s":{"a":0,"k":[100,100,100]}}]}],"ip":5,"op":60,"st":0,"bm":0,"nm":"Vector","parent":2,"hasMask":false},{"hd":false,"ty":4,"ddd":0,"ind":5,"sr":1,"ao":0,"ks":{"o":{"a":1,"k":[{"i":{"x":[0],"y":[0]},"o":{"x":[1],"y":[1]},"h":1,"t":0,"s":[0]},{"i":{"x":[0],"y":[0]},"o":{"x":[1],"y":[1]},"h":1,"t":1,"s":[0]},{"i":{"x":[0],"y":[0]},"o":{"x":[1],"y":[1]},"h":1,"t":2,"s":[0]},{"i":{"x":[0],"y":[0]},"o":{"x":[1],"y":[1]},"h":1,"t":3,"s":[0]},{"i":{"x":[0],"y":[0]},"o":{"x":[1],"y":[1]},"h":1,"t":4,"s":[0]},{"i":{"x":[0],"y":[0]},"o":{"x":[1],"y":[1]},"h":1,"t":5,"s":[0]},{"i":{"x":[0],"y":[0]},"o":{"x":[1],"y":[1]},"h":1,"t":6,"s":[0]},{"i":{"x":[0],"y":[0]},"o":{"x":[1],"y":[1]},"h":1,"t":7,"s":[0]},{"i":{"x":[0],"y":[0]},"o":{"x":[1],"y":[1]},"h":1,"t":8,"s":[0]},{"i":{"x":[0],"y":[0]},"o":{"x":[1],"y":[1]},"h":1,"t":9,"s":[0.20421302444736467]},{"i":{"x":[0],"y":[0]},"o":{"x":[1],"y":[1]},"h":1,"t":10,"s":[0.8908846918708793]},{"i":{"x":[0],"y":[0]},"o":{"x":[1],"y":[1]},"h":1,"t":11,"s":[2.21322192707766]},{"i":{"x":[0],"y":[0]},"o":{"x":[1],"y":[1]},"h":1,"t":12,"s":[4.418489554435204]},{"i":{"x":[0],"y":[0]},"o":{"x":[1],"y":[1]},"h":1,"t":13,"s":[7.9490449733617154]},{"i":{"x":[0],"y":[0]},"o":{"x":[1],"y":[1]},"h":1,"t":14,"s":[13.733638806968115]},{"i":{"x":[0],"y":[0]},"o":{"x":[1],"y":[1]},"h":1,"t":15,"s":[24.35423892026852]},{"i":{"x":[0],"y":[0]},"o":{"x":[1],"y":[1]},"h":1,"t":16,"s":[50]},{"i":{"x":[0],"y":[0]},"o":{"x":[1],"y":[1]},"h":1,"t":17,"s":[75.64576107973147]},{"i":{"x":[0],"y":[0]},"o":{"x":[1],"y":[1]},"h":1,"t":18,"s":[86.2663611930319]},{"i":{"x":[0],"y":[0]},"o":{"x":[1],"y":[1]},"h":1,"t":19,"s":[92.05095502663828]},{"i":{"x":[0],"y":[0]},"o":{"x":[1],"y":[1]},"h":1,"t":20,"s":[95.5815104455648]},{"i":{"x":[0],"y":[0]},"o":{"x":[1],"y":[1]},"h":1,"t":21,"s":[97.78677807292233]},{"i":{"x":[0],"y":[0]},"o":{"x":[1],"y":[1]},"h":1,"t":22,"s":[99.10911530812913]},{"i":{"x":[0],"y":[0]},"o":{"x":[1],"y":[1]},"h":1,"t":23,"s":[99.79578697555264]},{"i":{"x":[0],"y":[0]},"o":{"x":[1],"y":[1]},"h":1,"t":24,"s":[100]},{"i":{"x":[0],"y":[0]},"o":{"x":[1],"y":[1]},"h":1,"t":25,"s":[100]},{"i":{"x":[0],"y":[0]},"o":{"x":[1],"y":[1]},"h":1,"t":26,"s":[100]},{"i":{"x":[0],"y":[0]},"o":{"x":[1],"y":[1]},"h":1,"t":27,"s":[100]},{"i":{"x":[0],"y":[0]},"o":{"x":[1],"y":[1]},"h":1,"t":28,"s":[100]},{"i":{"x":[0],"y":[0]},"o":{"x":[1],"y":[1]},"h":1,"t":29,"s":[100]},{"i":{"x":[0],"y":[0]},"o":{"x":[1],"y":[1]},"h":1,"t":30,"s":[100]},{"i":{"x":[0],"y":[0]},"o":{"x":[1],"y":[1]},"h":1,"t":31,"s":[100]},{"i":{"x":[0],"y":[0]},"o":{"x":[1],"y":[1]},"h":1,"t":32,"s":[100]},{"i":{"x":[0],"y":[0]},"o":{"x":[1],"y":[1]},"h":1,"t":33,"s":[100]},{"i":{"x":[0],"y":[0]},"o":{"x":[1],"y":[1]},"h":1,"t":34,"s":[100]},{"i":{"x":[0],"y":[0]},"o":{"x":[1],"y":[1]},"h":1,"t":35,"s":[100]},{"i":{"x":[0],"y":[0]},"o":{"x":[1],"y":[1]},"h":1,"t":36,"s":[100]},{"i":{"x":[0],"y":[0]},"o":{"x":[1],"y":[1]},"h":1,"t":37,"s":[99.81996951841349]},{"i":{"x":[0],"y":[0]},"o":{"x":[1],"y":[1]},"h":1,"t":38,"s":[99.21930195991678]},{"i":{"x":[0],"y":[0]},"o":{"x":[1],"y":[1]},"h":1,"t":39,"s":[98.07552789183043]},{"i":{"x":[0],"y":[0]},"o":{"x":[1],"y":[1]},"h":1,"t":40,"s":[96.1985180370635]},{"i":{"x":[0],"y":[0]},"o":{"x":[1],"y":[1]},"h":1,"t":41,"s":[93.26690563755626]},{"i":{"x":[0],"y":[0]},"o":{"x":[1],"y":[1]},"h":1,"t":42,"s":[88.6645929534551]},{"i":{"x":[0],"y":[0]},"o":{"x":[1],"y":[1]},"h":1,"t":43,"s":[80.94133940622638]},{"i":{"x":[0],"y":[0]},"o":{"x":[1],"y":[1]},"h":1,"t":44,"s":[65.18642797601737]},{"i":{"x":[0],"y":[0]},"o":{"x":[1],"y":[1]},"h":1,"t":45,"s":[34.81357202398262]},{"i":{"x":[0],"y":[0]},"o":{"x":[1],"y":[1]},"h":1,"t":46,"s":[19.05866059377366]},{"i":{"x":[0],"y":[0]},"o":{"x":[1],"y":[1]},"h":1,"t":47,"s":[11.335407046544887]},{"i":{"x":[0],"y":[0]},"o":{"x":[1],"y":[1]},"h":1,"t":48,"s":[6.733094362443737]},{"i":{"x":[0],"y":[0]},"o":{"x":[1],"y":[1]},"h":1,"t":49,"s":[3.8014819629364927]},{"i":{"x":[0],"y":[0]},"o":{"x":[1],"y":[1]},"h":1,"t":50,"s":[1.9244721081695615]},{"i":{"x":[0],"y":[0]},"o":{"x":[1],"y":[1]},"h":1,"t":51,"s":[0.7806980400832275]},{"i":{"x":[0],"y":[0]},"o":{"x":[1],"y":[1]},"h":1,"t":52,"s":[0.1800304815865128]},{"i":{"x":[0],"y":[0]},"o":{"x":[1],"y":[1]},"h":1,"t":53,"s":[0]},{"i":{"x":[0],"y":[0]},"o":{"x":[1],"y":[1]},"h":1,"t":54,"s":[0]},{"i":{"x":[0],"y":[0]},"o":{"x":[1],"y":[1]},"h":1,"t":55,"s":[0]},{"i":{"x":[0],"y":[0]},"o":{"x":[1],"y":[1]},"h":1,"t":56,"s":[0]},{"i":{"x":[0],"y":[0]},"o":{"x":[1],"y":[1]},"h":1,"t":57,"s":[0]},{"i":{"x":[0],"y":[0]},"o":{"x":[1],"y":[1]},"h":1,"t":58,"s":[0]},{"i":{"x":[0],"y":[0]},"o":{"x":[1],"y":[1]},"h":1,"t":59,"s":[0]}]},"r":{"a":0,"k":0},"p":{"a":0,"k":[-161.25096130371094,21.311447143554688,0]},"a":{"a":0,"k":[0,0,0]},"s":{"a":0,"k":[99.99999403953552,99.99999403953552,100]},"sk":{"a":0,"k":0},"sa":{"a":0,"k":0}},"shapes":[{"ty":"gr","it":[{"ty":"sh","ks":{"a":0,"k":{"c":true,"v":[[-5.270921,-5.2709208],[5.270921,-5.2709208],[5.270921,5.2709208],[-5.270921,5.2709208]],"i":[[0,0],[0,0],[0,0],[0,0]],"o":[[0,0],[0,0],[0,0],[0,0]]}}},{"ty":"fl","o":{"a":0,"k":100},"c":{"a":0,"k":[0.00392156862745098,0.054901960784313725,0.24313725490196078]}},{"ty":"rd","r":{"a":0,"k":0}},{"ty":"tr","o":{"a":0,"k":100},"r":{"a":0,"k":0},"p":{"a":0,"k":[0,0,0]},"a":{"a":0,"k":[0,0,0]},"s":{"a":0,"k":[100,100,100]}}]}],"ip":8,"op":60,"st":0,"bm":0,"nm":"Vector","parent":2,"hasMask":false},{"hd":false,"ty":4,"ddd":0,"ind":6,"sr":1,"ao":0,"ks":{"o":{"a":1,"k":[{"i":{"x":[0],"y":[0]},"o":{"x":[1],"y":[1]},"h":1,"t":0,"s":[0]},{"i":{"x":[0],"y":[0]},"o":{"x":[1],"y":[1]},"h":1,"t":1,"s":[0]},{"i":{"x":[0],"y":[0]},"o":{"x":[1],"y":[1]},"h":1,"t":2,"s":[0]},{"i":{"x":[0],"y":[0]},"o":{"x":[1],"y":[1]},"h":1,"t":3,"s":[0]},{"i":{"x":[0],"y":[0]},"o":{"x":[1],"y":[1]},"h":1,"t":4,"s":[0]},{"i":{"x":[0],"y":[0]},"o":{"x":[1],"y":[1]},"h":1,"t":5,"s":[0]},{"i":{"x":[0],"y":[0]},"o":{"x":[1],"y":[1]},"h":1,"t":6,"s":[0]},{"i":{"x":[0],"y":[0]},"o":{"x":[1],"y":[1]},"h":1,"t":7,"s":[0.20421302444736467]},{"i":{"x":[0],"y":[0]},"o":{"x":[1],"y":[1]},"h":1,"t":8,"s":[0.8908846918708793]},{"i":{"x":[0],"y":[0]},"o":{"x":[1],"y":[1]},"h":1,"t":9,"s":[2.21322192707766]},{"i":{"x":[0],"y":[0]},"o":{"x":[1],"y":[1]},"h":1,"t":10,"s":[4.418489554435204]},{"i":{"x":[0],"y":[0]},"o":{"x":[1],"y":[1]},"h":1,"t":11,"s":[7.9490449733617154]},{"i":{"x":[0],"y":[0]},"o":{"x":[1],"y":[1]},"h":1,"t":12,"s":[13.733638806968115]},{"i":{"x":[0],"y":[0]},"o":{"x":[1],"y":[1]},"h":1,"t":13,"s":[24.35423892026852]},{"i":{"x":[0],"y":[0]},"o":{"x":[1],"y":[1]},"h":1,"t":14,"s":[50]},{"i":{"x":[0],"y":[0]},"o":{"x":[1],"y":[1]},"h":1,"t":15,"s":[75.64576107973147]},{"i":{"x":[0],"y":[0]},"o":{"x":[1],"y":[1]},"h":1,"t":16,"s":[86.2663611930319]},{"i":{"x":[0],"y":[0]},"o":{"x":[1],"y":[1]},"h":1,"t":17,"s":[92.05095502663828]},{"i":{"x":[0],"y":[0]},"o":{"x":[1],"y":[1]},"h":1,"t":18,"s":[95.5815104455648]},{"i":{"x":[0],"y":[0]},"o":{"x":[1],"y":[1]},"h":1,"t":19,"s":[97.78677807292233]},{"i":{"x":[0],"y":[0]},"o":{"x":[1],"y":[1]},"h":1,"t":20,"s":[99.10911530812913]},{"i":{"x":[0],"y":[0]},"o":{"x":[1],"y":[1]},"h":1,"t":21,"s":[99.79578697555264]},{"i":{"x":[0],"y":[0]},"o":{"x":[1],"y":[1]},"h":1,"t":22,"s":[100]},{"i":{"x":[0],"y":[0]},"o":{"x":[1],"y":[1]},"h":1,"t":23,"s":[100]},{"i":{"x":[0],"y":[0]},"o":{"x":[1],"y":[1]},"h":1,"t":24,"s":[100]},{"i":{"x":[0],"y":[0]},"o":{"x":[1],"y":[1]},"h":1,"t":25,"s":[100]},{"i":{"x":[0],"y":[0]},"o":{"x":[1],"y":[1]},"h":1,"t":26,"s":[100]},{"i":{"x":[0],"y":[0]},"o":{"x":[1],"y":[1]},"h":1,"t":27,"s":[100]},{"i":{"x":[0],"y":[0]},"o":{"x":[1],"y":[1]},"h":1,"t":28,"s":[100]},{"i":{"x":[0],"y":[0]},"o":{"x":[1],"y":[1]},"h":1,"t":29,"s":[100]},{"i":{"x":[0],"y":[0]},"o":{"x":[1],"y":[1]},"h":1,"t":30,"s":[100]},{"i":{"x":[0],"y":[0]},"o":{"x":[1],"y":[1]},"h":1,"t":31,"s":[100]},{"i":{"x":[0],"y":[0]},"o":{"x":[1],"y":[1]},"h":1,"t":32,"s":[100]},{"i":{"x":[0],"y":[0]},"o":{"x":[1],"y":[1]},"h":1,"t":33,"s":[100]},{"i":{"x":[0],"y":[0]},"o":{"x":[1],"y":[1]},"h":1,"t":34,"s":[100]},{"i":{"x":[0],"y":[0]},"o":{"x":[1],"y":[1]},"h":1,"t":35,"s":[99.81996951841349]},{"i":{"x":[0],"y":[0]},"o":{"x":[1],"y":[1]},"h":1,"t":36,"s":[99.21930195991678]},{"i":{"x":[0],"y":[0]},"o":{"x":[1],"y":[1]},"h":1,"t":37,"s":[98.07552789183043]},{"i":{"x":[0],"y":[0]},"o":{"x":[1],"y":[1]},"h":1,"t":38,"s":[96.1985180370635]},{"i":{"x":[0],"y":[0]},"o":{"x":[1],"y":[1]},"h":1,"t":39,"s":[93.26690563755626]},{"i":{"x":[0],"y":[0]},"o":{"x":[1],"y":[1]},"h":1,"t":40,"s":[88.6645929534551]},{"i":{"x":[0],"y":[0]},"o":{"x":[1],"y":[1]},"h":1,"t":41,"s":[80.94133940622638]},{"i":{"x":[0],"y":[0]},"o":{"x":[1],"y":[1]},"h":1,"t":42,"s":[65.18642797601737]},{"i":{"x":[0],"y":[0]},"o":{"x":[1],"y":[1]},"h":1,"t":43,"s":[34.81357202398262]},{"i":{"x":[0],"y":[0]},"o":{"x":[1],"y":[1]},"h":1,"t":44,"s":[19.05866059377366]},{"i":{"x":[0],"y":[0]},"o":{"x":[1],"y":[1]},"h":1,"t":45,"s":[11.335407046544887]},{"i":{"x":[0],"y":[0]},"o":{"x":[1],"y":[1]},"h":1,"t":46,"s":[6.733094362443737]},{"i":{"x":[0],"y":[0]},"o":{"x":[1],"y":[1]},"h":1,"t":47,"s":[3.8014819629364927]},{"i":{"x":[0],"y":[0]},"o":{"x":[1],"y":[1]},"h":1,"t":48,"s":[1.9244721081695615]},{"i":{"x":[0],"y":[0]},"o":{"x":[1],"y":[1]},"h":1,"t":49,"s":[0.7806980400832275]},{"i":{"x":[0],"y":[0]},"o":{"x":[1],"y":[1]},"h":1,"t":50,"s":[0.1800304815865128]},{"i":{"x":[0],"y":[0]},"o":{"x":[1],"y":[1]},"h":1,"t":51,"s":[0]},{"i":{"x":[0],"y":[0]},"o":{"x":[1],"y":[1]},"h":1,"t":52,"s":[0]},{"i":{"x":[0],"y":[0]},"o":{"x":[1],"y":[1]},"h":1,"t":53,"s":[0]},{"i":{"x":[0],"y":[0]},"o":{"x":[1],"y":[1]},"h":1,"t":54,"s":[0]},{"i":{"x":[0],"y":[0]},"o":{"x":[1],"y":[1]},"h":1,"t":55,"s":[0]},{"i":{"x":[0],"y":[0]},"o":{"x":[1],"y":[1]},"h":1,"t":56,"s":[0]},{"i":{"x":[0],"y":[0]},"o":{"x":[1],"y":[1]},"h":1,"t":57,"s":[0]},{"i":{"x":[0],"y":[0]},"o":{"x":[1],"y":[1]},"h":1,"t":58,"s":[0]},{"i":{"x":[0],"y":[0]},"o":{"x":[1],"y":[1]},"h":1,"t":59,"s":[0]}]},"r":{"a":0,"k":0},"p":{"a":0,"k":[-138.98046875,-21.694549560546875,0]},"a":{"a":0,"k":[0,0,0]},"s":{"a":0,"k":[100,100,100]},"sk":{"a":0,"k":0},"sa":{"a":0,"k":0}},"shapes":[{"ty":"gr","it":[{"ty":"sh","ks":{"a":0,"k":{"c":true,"v":[[-5.5637503,-5.5637503],[5.5637503,-5.5637503],[5.5637503,5.5637503],[-5.5637503,5.5637503]],"i":[[0,0],[0,0],[0,0],[0,0]],"o":[[0,0],[0,0],[0,0],[0,0]]}}},{"ty":"fl","o":{"a":0,"k":100},"c":{"a":0,"k":[0.00392156862745098,0.054901960784313725,0.24313725490196078]}},{"ty":"rd","r":{"a":0,"k":0}},{"ty":"tr","o":{"a":0,"k":100},"r":{"a":0,"k":0},"p":{"a":0,"k":[0,0,0]},"a":{"a":0,"k":[0,0,0]},"s":{"a":0,"k":[100,100,100]}}]}],"ip":6,"op":60,"st":0,"bm":0,"nm":"Vector","parent":2,"hasMask":false},{"hd":false,"ty":4,"ddd":0,"ind":7,"sr":1,"ao":0,"ks":{"o":{"a":1,"k":[{"i":{"x":[0],"y":[0]},"o":{"x":[1],"y":[1]},"h":1,"t":0,"s":[0]},{"i":{"x":[0],"y":[0]},"o":{"x":[1],"y":[1]},"h":1,"t":1,"s":[0]},{"i":{"x":[0],"y":[0]},"o":{"x":[1],"y":[1]},"h":1,"t":2,"s":[0.20421302444736467]},{"i":{"x":[0],"y":[0]},"o":{"x":[1],"y":[1]},"h":1,"t":3,"s":[0.8908846918708793]},{"i":{"x":[0],"y":[0]},"o":{"x":[1],"y":[1]},"h":1,"t":4,"s":[2.21322192707766]},{"i":{"x":[0],"y":[0]},"o":{"x":[1],"y":[1]},"h":1,"t":5,"s":[4.418489554435204]},{"i":{"x":[0],"y":[0]},"o":{"x":[1],"y":[1]},"h":1,"t":6,"s":[7.9490449733617154]},{"i":{"x":[0],"y":[0]},"o":{"x":[1],"y":[1]},"h":1,"t":7,"s":[13.733638806968115]},{"i":{"x":[0],"y":[0]},"o":{"x":[1],"y":[1]},"h":1,"t":8,"s":[24.35423892026852]},{"i":{"x":[0],"y":[0]},"o":{"x":[1],"y":[1]},"h":1,"t":9,"s":[50]},{"i":{"x":[0],"y":[0]},"o":{"x":[1],"y":[1]},"h":1,"t":10,"s":[75.64576107973147]},{"i":{"x":[0],"y":[0]},"o":{"x":[1],"y":[1]},"h":1,"t":11,"s":[86.2663611930319]},{"i":{"x":[0],"y":[0]},"o":{"x":[1],"y":[1]},"h":1,"t":12,"s":[92.05095502663828]},{"i":{"x":[0],"y":[0]},"o":{"x":[1],"y":[1]},"h":1,"t":13,"s":[95.5815104455648]},{"i":{"x":[0],"y":[0]},"o":{"x":[1],"y":[1]},"h":1,"t":14,"s":[97.78677807292233]},{"i":{"x":[0],"y":[0]},"o":{"x":[1],"y":[1]},"h":1,"t":15,"s":[99.10911530812913]},{"i":{"x":[0],"y":[0]},"o":{"x":[1],"y":[1]},"h":1,"t":16,"s":[99.79578697555264]},{"i":{"x":[0],"y":[0]},"o":{"x":[1],"y":[1]},"h":1,"t":17,"s":[100]},{"i":{"x":[0],"y":[0]},"o":{"x":[1],"y":[1]},"h":1,"t":18,"s":[100]},{"i":{"x":[0],"y":[0]},"o":{"x":[1],"y":[1]},"h":1,"t":19,"s":[100]},{"i":{"x":[0],"y":[0]},"o":{"x":[1],"y":[1]},"h":1,"t":20,"s":[100]},{"i":{"x":[0],"y":[0]},"o":{"x":[1],"y":[1]},"h":1,"t":21,"s":[100]},{"i":{"x":[0],"y":[0]},"o":{"x":[1],"y":[1]},"h":1,"t":22,"s":[100]},{"i":{"x":[0],"y":[0]},"o":{"x":[1],"y":[1]},"h":1,"t":23,"s":[100]},{"i":{"x":[0],"y":[0]},"o":{"x":[1],"y":[1]},"h":1,"t":24,"s":[100]},{"i":{"x":[0],"y":[0]},"o":{"x":[1],"y":[1]},"h":1,"t":25,"s":[100]},{"i":{"x":[0],"y":[0]},"o":{"x":[1],"y":[1]},"h":1,"t":26,"s":[100]},{"i":{"x":[0],"y":[0]},"o":{"x":[1],"y":[1]},"h":1,"t":27,"s":[100]},{"i":{"x":[0],"y":[0]},"o":{"x":[1],"y":[1]},"h":1,"t":28,"s":[100]},{"i":{"x":[0],"y":[0]},"o":{"x":[1],"y":[1]},"h":1,"t":29,"s":[100]},{"i":{"x":[0],"y":[0]},"o":{"x":[1],"y":[1]},"h":1,"t":30,"s":[99.81996951841349]},{"i":{"x":[0],"y":[0]},"o":{"x":[1],"y":[1]},"h":1,"t":31,"s":[99.21930195991678]},{"i":{"x":[0],"y":[0]},"o":{"x":[1],"y":[1]},"h":1,"t":32,"s":[98.07552789183043]},{"i":{"x":[0],"y":[0]},"o":{"x":[1],"y":[1]},"h":1,"t":33,"s":[96.1985180370635]},{"i":{"x":[0],"y":[0]},"o":{"x":[1],"y":[1]},"h":1,"t":34,"s":[93.26690563755626]},{"i":{"x":[0],"y":[0]},"o":{"x":[1],"y":[1]},"h":1,"t":35,"s":[88.6645929534551]},{"i":{"x":[0],"y":[0]},"o":{"x":[1],"y":[1]},"h":1,"t":36,"s":[80.94133940622638]},{"i":{"x":[0],"y":[0]},"o":{"x":[1],"y":[1]},"h":1,"t":37,"s":[65.18642797601737]},{"i":{"x":[0],"y":[0]},"o":{"x":[1],"y":[1]},"h":1,"t":38,"s":[34.81357202398262]},{"i":{"x":[0],"y":[0]},"o":{"x":[1],"y":[1]},"h":1,"t":39,"s":[19.05866059377366]},{"i":{"x":[0],"y":[0]},"o":{"x":[1],"y":[1]},"h":1,"t":40,"s":[11.335407046544887]},{"i":{"x":[0],"y":[0]},"o":{"x":[1],"y":[1]},"h":1,"t":41,"s":[6.733094362443737]},{"i":{"x":[0],"y":[0]},"o":{"x":[1],"y":[1]},"h":1,"t":42,"s":[3.8014819629364927]},{"i":{"x":[0],"y":[0]},"o":{"x":[1],"y":[1]},"h":1,"t":43,"s":[1.9244721081695615]},{"i":{"x":[0],"y":[0]},"o":{"x":[1],"y":[1]},"h":1,"t":44,"s":[0.7806980400832275]},{"i":{"x":[0],"y":[0]},"o":{"x":[1],"y":[1]},"h":1,"t":45,"s":[0.1800304815865128]},{"i":{"x":[0],"y":[0]},"o":{"x":[1],"y":[1]},"h":1,"t":46,"s":[0]},{"i":{"x":[0],"y":[0]},"o":{"x":[1],"y":[1]},"h":1,"t":47,"s":[0]},{"i":{"x":[0],"y":[0]},"o":{"x":[1],"y":[1]},"h":1,"t":48,"s":[0]},{"i":{"x":[0],"y":[0]},"o":{"x":[1],"y":[1]},"h":1,"t":49,"s":[0]},{"i":{"x":[0],"y":[0]},"o":{"x":[1],"y":[1]},"h":1,"t":50,"s":[0]},{"i":{"x":[0],"y":[0]},"o":{"x":[1],"y":[1]},"h":1,"t":51,"s":[0]},{"i":{"x":[0],"y":[0]},"o":{"x":[1],"y":[1]},"h":1,"t":52,"s":[0]},{"i":{"x":[0],"y":[0]},"o":{"x":[1],"y":[1]},"h":1,"t":53,"s":[0]},{"i":{"x":[0],"y":[0]},"o":{"x":[1],"y":[1]},"h":1,"t":54,"s":[0]},{"i":{"x":[0],"y":[0]},"o":{"x":[1],"y":[1]},"h":1,"t":55,"s":[0]},{"i":{"x":[0],"y":[0]},"o":{"x":[1],"y":[1]},"h":1,"t":56,"s":[0]},{"i":{"x":[0],"y":[0]},"o":{"x":[1],"y":[1]},"h":1,"t":57,"s":[0]},{"i":{"x":[0],"y":[0]},"o":{"x":[1],"y":[1]},"h":1,"t":58,"s":[0]},{"i":{"x":[0],"y":[0]},"o":{"x":[1],"y":[1]},"h":1,"t":59,"s":[0]}]},"r":{"a":0,"k":0},"p":{"a":0,"k":[-138.98046875,-0.040313720703125,0]},"a":{"a":0,"k":[0,0,0]},"s":{"a":0,"k":[100,100,100]},"sk":{"a":0,"k":0},"sa":{"a":0,"k":0}},"shapes":[{"ty":"gr","it":[{"ty":"sh","ks":{"a":0,"k":{"c":true,"v":[[-5.2709208,-5.2709208],[5.2709208,-5.2709208],[5.2709208,5.2709208],[-5.2709208,5.2709208]],"i":[[0,0],[0,0],[0,0],[0,0]],"o":[[0,0],[0,0],[0,0],[0,0]]}}},{"ty":"fl","o":{"a":0,"k":100},"c":{"a":0,"k":[0.00392156862745098,0.054901960784313725,0.24313725490196078]}},{"ty":"rd","r":{"a":0,"k":0}},{"ty":"tr","o":{"a":0,"k":100},"r":{"a":0,"k":0},"p":{"a":0,"k":[0,0,0]},"a":{"a":0,"k":[0,0,0]},"s":{"a":0,"k":[100,100,100]}}]}],"ip":1,"op":60,"st":0,"bm":0,"nm":"Vector","parent":2,"hasMask":false},{"hd":false,"ty":4,"ddd":0,"ind":8,"sr":1,"ao":0,"ks":{"o":{"a":1,"k":[{"i":{"x":[0],"y":[0]},"o":{"x":[1],"y":[1]},"h":1,"t":0,"s":[0]},{"i":{"x":[0],"y":[0]},"o":{"x":[1],"y":[1]},"h":1,"t":1,"s":[0]},{"i":{"x":[0],"y":[0]},"o":{"x":[1],"y":[1]},"h":1,"t":2,"s":[0]},{"i":{"x":[0],"y":[0]},"o":{"x":[1],"y":[1]},"h":1,"t":3,"s":[0]},{"i":{"x":[0],"y":[0]},"o":{"x":[1],"y":[1]},"h":1,"t":4,"s":[0]},{"i":{"x":[0],"y":[0]},"o":{"x":[1],"y":[1]},"h":1,"t":5,"s":[0.20421302444736467]},{"i":{"x":[0],"y":[0]},"o":{"x":[1],"y":[1]},"h":1,"t":6,"s":[0.8908846918708793]},{"i":{"x":[0],"y":[0]},"o":{"x":[1],"y":[1]},"h":1,"t":7,"s":[2.21322192707766]},{"i":{"x":[0],"y":[0]},"o":{"x":[1],"y":[1]},"h":1,"t":8,"s":[4.418489554435204]},{"i":{"x":[0],"y":[0]},"o":{"x":[1],"y":[1]},"h":1,"t":9,"s":[7.9490449733617154]},{"i":{"x":[0],"y":[0]},"o":{"x":[1],"y":[1]},"h":1,"t":10,"s":[13.733638806968115]},{"i":{"x":[0],"y":[0]},"o":{"x":[1],"y":[1]},"h":1,"t":11,"s":[24.35423892026852]},{"i":{"x":[0],"y":[0]},"o":{"x":[1],"y":[1]},"h":1,"t":12,"s":[50]},{"i":{"x":[0],"y":[0]},"o":{"x":[1],"y":[1]},"h":1,"t":13,"s":[75.64576107973147]},{"i":{"x":[0],"y":[0]},"o":{"x":[1],"y":[1]},"h":1,"t":14,"s":[86.2663611930319]},{"i":{"x":[0],"y":[0]},"o":{"x":[1],"y":[1]},"h":1,"t":15,"s":[92.05095502663828]},{"i":{"x":[0],"y":[0]},"o":{"x":[1],"y":[1]},"h":1,"t":16,"s":[95.5815104455648]},{"i":{"x":[0],"y":[0]},"o":{"x":[1],"y":[1]},"h":1,"t":17,"s":[97.78677807292233]},{"i":{"x":[0],"y":[0]},"o":{"x":[1],"y":[1]},"h":1,"t":18,"s":[99.10911530812913]},{"i":{"x":[0],"y":[0]},"o":{"x":[1],"y":[1]},"h":1,"t":19,"s":[99.79578697555264]},{"i":{"x":[0],"y":[0]},"o":{"x":[1],"y":[1]},"h":1,"t":20,"s":[100]},{"i":{"x":[0],"y":[0]},"o":{"x":[1],"y":[1]},"h":1,"t":21,"s":[100]},{"i":{"x":[0],"y":[0]},"o":{"x":[1],"y":[1]},"h":1,"t":22,"s":[100]},{"i":{"x":[0],"y":[0]},"o":{"x":[1],"y":[1]},"h":1,"t":23,"s":[100]},{"i":{"x":[0],"y":[0]},"o":{"x":[1],"y":[1]},"h":1,"t":24,"s":[100]},{"i":{"x":[0],"y":[0]},"o":{"x":[1],"y":[1]},"h":1,"t":25,"s":[100]},{"i":{"x":[0],"y":[0]},"o":{"x":[1],"y":[1]},"h":1,"t":26,"s":[100]},{"i":{"x":[0],"y":[0]},"o":{"x":[1],"y":[1]},"h":1,"t":27,"s":[100]},{"i":{"x":[0],"y":[0]},"o":{"x":[1],"y":[1]},"h":1,"t":28,"s":[100]},{"i":{"x":[0],"y":[0]},"o":{"x":[1],"y":[1]},"h":1,"t":29,"s":[100]},{"i":{"x":[0],"y":[0]},"o":{"x":[1],"y":[1]},"h":1,"t":30,"s":[100]},{"i":{"x":[0],"y":[0]},"o":{"x":[1],"y":[1]},"h":1,"t":31,"s":[100]},{"i":{"x":[0],"y":[0]},"o":{"x":[1],"y":[1]},"h":1,"t":32,"s":[100]},{"i":{"x":[0],"y":[0]},"o":{"x":[1],"y":[1]},"h":1,"t":33,"s":[99.81996951841349]},{"i":{"x":[0],"y":[0]},"o":{"x":[1],"y":[1]},"h":1,"t":34,"s":[99.21930195991678]},{"i":{"x":[0],"y":[0]},"o":{"x":[1],"y":[1]},"h":1,"t":35,"s":[98.07552789183043]},{"i":{"x":[0],"y":[0]},"o":{"x":[1],"y":[1]},"h":1,"t":36,"s":[96.1985180370635]},{"i":{"x":[0],"y":[0]},"o":{"x":[1],"y":[1]},"h":1,"t":37,"s":[93.26690563755626]},{"i":{"x":[0],"y":[0]},"o":{"x":[1],"y":[1]},"h":1,"t":38,"s":[88.6645929534551]},{"i":{"x":[0],"y":[0]},"o":{"x":[1],"y":[1]},"h":1,"t":39,"s":[80.94133940622638]},{"i":{"x":[0],"y":[0]},"o":{"x":[1],"y":[1]},"h":1,"t":40,"s":[65.18642797601737]},{"i":{"x":[0],"y":[0]},"o":{"x":[1],"y":[1]},"h":1,"t":41,"s":[34.81357202398262]},{"i":{"x":[0],"y":[0]},"o":{"x":[1],"y":[1]},"h":1,"t":42,"s":[19.05866059377366]},{"i":{"x":[0],"y":[0]},"o":{"x":[1],"y":[1]},"h":1,"t":43,"s":[11.335407046544887]},{"i":{"x":[0],"y":[0]},"o":{"x":[1],"y":[1]},"h":1,"t":44,"s":[6.733094362443737]},{"i":{"x":[0],"y":[0]},"o":{"x":[1],"y":[1]},"h":1,"t":45,"s":[3.8014819629364927]},{"i":{"x":[0],"y":[0]},"o":{"x":[1],"y":[1]},"h":1,"t":46,"s":[1.9244721081695615]},{"i":{"x":[0],"y":[0]},"o":{"x":[1],"y":[1]},"h":1,"t":47,"s":[0.7806980400832275]},{"i":{"x":[0],"y":[0]},"o":{"x":[1],"y":[1]},"h":1,"t":48,"s":[0.1800304815865128]},{"i":{"x":[0],"y":[0]},"o":{"x":[1],"y":[1]},"h":1,"t":49,"s":[0]},{"i":{"x":[0],"y":[0]},"o":{"x":[1],"y":[1]},"h":1,"t":50,"s":[0]},{"i":{"x":[0],"y":[0]},"o":{"x":[1],"y":[1]},"h":1,"t":51,"s":[0]},{"i":{"x":[0],"y":[0]},"o":{"x":[1],"y":[1]},"h":1,"t":52,"s":[0]},{"i":{"x":[0],"y":[0]},"o":{"x":[1],"y":[1]},"h":1,"t":53,"s":[0]},{"i":{"x":[0],"y":[0]},"o":{"x":[1],"y":[1]},"h":1,"t":54,"s":[0]},{"i":{"x":[0],"y":[0]},"o":{"x":[1],"y":[1]},"h":1,"t":55,"s":[0]},{"i":{"x":[0],"y":[0]},"o":{"x":[1],"y":[1]},"h":1,"t":56,"s":[0]},{"i":{"x":[0],"y":[0]},"o":{"x":[1],"y":[1]},"h":1,"t":57,"s":[0]},{"i":{"x":[0],"y":[0]},"o":{"x":[1],"y":[1]},"h":1,"t":58,"s":[0]},{"i":{"x":[0],"y":[0]},"o":{"x":[1],"y":[1]},"h":1,"t":59,"s":[0]}]},"r":{"a":0,"k":0},"p":{"a":0,"k":[-138.9384765625,22.23199462890625,0]},"a":{"a":0,"k":[0,0,0]},"s":{"a":0,"k":[100,100,100]},"sk":{"a":0,"k":0},"sa":{"a":0,"k":0}},"shapes":[{"ty":"gr","it":[{"ty":"sh","ks":{"a":0,"k":{"c":true,"v":[[3.6101422,-2.4825344],[4.35043,-0.04233122],[3.0637546,3.064219],[-0.04218626,4.350281],[-2.4826984,3.609993],[-4.1004,1.6391788],[-4.3504305,-0.8992009],[-3.148119,-3.1479673],[-0.8990412,-4.3502812],[1.6387229,-4.0999374]],"i":[[-0.48288819999999966,-0.7221844000000002],[0,-0.86851883],[0.8237275999999998,-0.8240370000000001],[1.16488166,0],[0.7224881999999999,0.48319800000000024],[0.33256149999999973,0.8022574999999998],[-0.1693511000000001,0.852570517],[-0.6145005000000001,0.6141909999999999],[-0.852267,0.1699642000000008],[-0.8025608000000001,-0.3328652999999999]],"o":[[0.4825792999999998,0.7221844],[0,1.1651854199999998],[-0.8237334000000001,0.8231148999999998],[-0.8688283,0],[-0.7221846000000003,-0.48257879999999975],[-0.3325615000000006,-0.8028703],[0.16965490000000027,-0.8519576000000001],[0.6141909999999999,-0.6141911000000002],[0.851957822,-0.1693453999999992],[0.8025613,0.3322522000000001]]}}},{"ty":"fl","o":{"a":0,"k":100},"c":{"a":0,"k":[0.00392156862745098,0.054901960784313725,0.24313725490196078]}},{"ty":"rd","r":{"a":0,"k":0}},{"ty":"tr","o":{"a":0,"k":100},"r":{"a":0,"k":0},"p":{"a":0,"k":[0,0,0]},"a":{"a":0,"k":[0,0,0]},"s":{"a":0,"k":[100,100,100]}}]}],"ip":4,"op":60,"st":0,"bm":0,"nm":"Vector","parent":2,"hasMask":false},{"hd":false,"ty":4,"ddd":0,"ind":9,"sr":1,"ao":0,"ks":{"o":{"a":1,"k":[{"i":{"x":[0],"y":[0]},"o":{"x":[1],"y":[1]},"h":1,"t":0,"s":[0]},{"i":{"x":[0],"y":[0]},"o":{"x":[1],"y":[1]},"h":1,"t":1,"s":[0]},{"i":{"x":[0],"y":[0]},"o":{"x":[1],"y":[1]},"h":1,"t":2,"s":[0]},{"i":{"x":[0],"y":[0]},"o":{"x":[1],"y":[1]},"h":1,"t":3,"s":[0.20421302444736467]},{"i":{"x":[0],"y":[0]},"o":{"x":[1],"y":[1]},"h":1,"t":4,"s":[0.8908846918708793]},{"i":{"x":[0],"y":[0]},"o":{"x":[1],"y":[1]},"h":1,"t":5,"s":[2.21322192707766]},{"i":{"x":[0],"y":[0]},"o":{"x":[1],"y":[1]},"h":1,"t":6,"s":[4.418489554435204]},{"i":{"x":[0],"y":[0]},"o":{"x":[1],"y":[1]},"h":1,"t":7,"s":[7.9490449733617154]},{"i":{"x":[0],"y":[0]},"o":{"x":[1],"y":[1]},"h":1,"t":8,"s":[13.733638806968115]},{"i":{"x":[0],"y":[0]},"o":{"x":[1],"y":[1]},"h":1,"t":9,"s":[24.35423892026852]},{"i":{"x":[0],"y":[0]},"o":{"x":[1],"y":[1]},"h":1,"t":10,"s":[50]},{"i":{"x":[0],"y":[0]},"o":{"x":[1],"y":[1]},"h":1,"t":11,"s":[75.64576107973147]},{"i":{"x":[0],"y":[0]},"o":{"x":[1],"y":[1]},"h":1,"t":12,"s":[86.2663611930319]},{"i":{"x":[0],"y":[0]},"o":{"x":[1],"y":[1]},"h":1,"t":13,"s":[92.05095502663828]},{"i":{"x":[0],"y":[0]},"o":{"x":[1],"y":[1]},"h":1,"t":14,"s":[95.5815104455648]},{"i":{"x":[0],"y":[0]},"o":{"x":[1],"y":[1]},"h":1,"t":15,"s":[97.78677807292233]},{"i":{"x":[0],"y":[0]},"o":{"x":[1],"y":[1]},"h":1,"t":16,"s":[99.10911530812913]},{"i":{"x":[0],"y":[0]},"o":{"x":[1],"y":[1]},"h":1,"t":17,"s":[99.79578697555264]},{"i":{"x":[0],"y":[0]},"o":{"x":[1],"y":[1]},"h":1,"t":18,"s":[100]},{"i":{"x":[0],"y":[0]},"o":{"x":[1],"y":[1]},"h":1,"t":19,"s":[100]},{"i":{"x":[0],"y":[0]},"o":{"x":[1],"y":[1]},"h":1,"t":20,"s":[100]},{"i":{"x":[0],"y":[0]},"o":{"x":[1],"y":[1]},"h":1,"t":21,"s":[100]},{"i":{"x":[0],"y":[0]},"o":{"x":[1],"y":[1]},"h":1,"t":22,"s":[100]},{"i":{"x":[0],"y":[0]},"o":{"x":[1],"y":[1]},"h":1,"t":23,"s":[100]},{"i":{"x":[0],"y":[0]},"o":{"x":[1],"y":[1]},"h":1,"t":24,"s":[100]},{"i":{"x":[0],"y":[0]},"o":{"x":[1],"y":[1]},"h":1,"t":25,"s":[100]},{"i":{"x":[0],"y":[0]},"o":{"x":[1],"y":[1]},"h":1,"t":26,"s":[100]},{"i":{"x":[0],"y":[0]},"o":{"x":[1],"y":[1]},"h":1,"t":27,"s":[100]},{"i":{"x":[0],"y":[0]},"o":{"x":[1],"y":[1]},"h":1,"t":28,"s":[100]},{"i":{"x":[0],"y":[0]},"o":{"x":[1],"y":[1]},"h":1,"t":29,"s":[100]},{"i":{"x":[0],"y":[0]},"o":{"x":[1],"y":[1]},"h":1,"t":30,"s":[100]},{"i":{"x":[0],"y":[0]},"o":{"x":[1],"y":[1]},"h":1,"t":31,"s":[99.81996951841349]},{"i":{"x":[0],"y":[0]},"o":{"x":[1],"y":[1]},"h":1,"t":32,"s":[99.21930195991678]},{"i":{"x":[0],"y":[0]},"o":{"x":[1],"y":[1]},"h":1,"t":33,"s":[98.07552789183043]},{"i":{"x":[0],"y":[0]},"o":{"x":[1],"y":[1]},"h":1,"t":34,"s":[96.1985180370635]},{"i":{"x":[0],"y":[0]},"o":{"x":[1],"y":[1]},"h":1,"t":35,"s":[93.26690563755626]},{"i":{"x":[0],"y":[0]},"o":{"x":[1],"y":[1]},"h":1,"t":36,"s":[88.6645929534551]},{"i":{"x":[0],"y":[0]},"o":{"x":[1],"y":[1]},"h":1,"t":37,"s":[80.94133940622638]},{"i":{"x":[0],"y":[0]},"o":{"x":[1],"y":[1]},"h":1,"t":38,"s":[65.18642797601737]},{"i":{"x":[0],"y":[0]},"o":{"x":[1],"y":[1]},"h":1,"t":39,"s":[34.81357202398262]},{"i":{"x":[0],"y":[0]},"o":{"x":[1],"y":[1]},"h":1,"t":40,"s":[19.05866059377366]},{"i":{"x":[0],"y":[0]},"o":{"x":[1],"y":[1]},"h":1,"t":41,"s":[11.335407046544887]},{"i":{"x":[0],"y":[0]},"o":{"x":[1],"y":[1]},"h":1,"t":42,"s":[6.733094362443737]},{"i":{"x":[0],"y":[0]},"o":{"x":[1],"y":[1]},"h":1,"t":43,"s":[3.8014819629364927]},{"i":{"x":[0],"y":[0]},"o":{"x":[1],"y":[1]},"h":1,"t":44,"s":[1.9244721081695615]},{"i":{"x":[0],"y":[0]},"o":{"x":[1],"y":[1]},"h":1,"t":45,"s":[0.7806980400832275]},{"i":{"x":[0],"y":[0]},"o":{"x":[1],"y":[1]},"h":1,"t":46,"s":[0.1800304815865128]},{"i":{"x":[0],"y":[0]},"o":{"x":[1],"y":[1]},"h":1,"t":47,"s":[0]},{"i":{"x":[0],"y":[0]},"o":{"x":[1],"y":[1]},"h":1,"t":48,"s":[0]},{"i":{"x":[0],"y":[0]},"o":{"x":[1],"y":[1]},"h":1,"t":49,"s":[0]},{"i":{"x":[0],"y":[0]},"o":{"x":[1],"y":[1]},"h":1,"t":50,"s":[0]},{"i":{"x":[0],"y":[0]},"o":{"x":[1],"y":[1]},"h":1,"t":51,"s":[0]},{"i":{"x":[0],"y":[0]},"o":{"x":[1],"y":[1]},"h":1,"t":52,"s":[0]},{"i":{"x":[0],"y":[0]},"o":{"x":[1],"y":[1]},"h":1,"t":53,"s":[0]},{"i":{"x":[0],"y":[0]},"o":{"x":[1],"y":[1]},"h":1,"t":54,"s":[0]},{"i":{"x":[0],"y":[0]},"o":{"x":[1],"y":[1]},"h":1,"t":55,"s":[0]},{"i":{"x":[0],"y":[0]},"o":{"x":[1],"y":[1]},"h":1,"t":56,"s":[0]},{"i":{"x":[0],"y":[0]},"o":{"x":[1],"y":[1]},"h":1,"t":57,"s":[0]},{"i":{"x":[0],"y":[0]},"o":{"x":[1],"y":[1]},"h":1,"t":58,"s":[0]},{"i":{"x":[0],"y":[0]},"o":{"x":[1],"y":[1]},"h":1,"t":59,"s":[0]}]},"r":{"a":0,"k":0},"p":{"a":0,"k":[-117.9521484375,-21.98736572265625,0]},"a":{"a":0,"k":[0,0,0]},"s":{"a":0,"k":[100,100,100]},"sk":{"a":0,"k":0},"sa":{"a":0,"k":0}},"shapes":[{"ty":"gr","it":[{"ty":"sh","ks":{"a":0,"k":{"c":true,"v":[[-5.2709208,-5.2709208],[5.2709208,-5.2709208],[5.2709208,5.2709208],[-5.2709208,5.2709208]],"i":[[0,0],[0,0],[0,0],[0,0]],"o":[[0,0],[0,0],[0,0],[0,0]]}}},{"ty":"fl","o":{"a":0,"k":100},"c":{"a":0,"k":[0.00392156862745098,0.054901960784313725,0.24313725490196078]}},{"ty":"rd","r":{"a":0,"k":0}},{"ty":"tr","o":{"a":0,"k":100},"r":{"a":0,"k":0},"p":{"a":0,"k":[0,0,0]},"a":{"a":0,"k":[0,0,0]},"s":{"a":0,"k":[100,100,100]}}]}],"ip":2,"op":60,"st":0,"bm":0,"nm":"Vector","parent":2,"hasMask":false},{"hd":false,"ty":4,"ddd":0,"ind":10,"sr":1,"ao":0,"ks":{"o":{"a":1,"k":[{"i":{"x":[0],"y":[0]},"o":{"x":[1],"y":[1]},"h":1,"t":0,"s":[0]},{"i":{"x":[0],"y":[0]},"o":{"x":[1],"y":[1]},"h":1,"t":1,"s":[0]},{"i":{"x":[0],"y":[0]},"o":{"x":[1],"y":[1]},"h":1,"t":2,"s":[0]},{"i":{"x":[0],"y":[0]},"o":{"x":[1],"y":[1]},"h":1,"t":3,"s":[0]},{"i":{"x":[0],"y":[0]},"o":{"x":[1],"y":[1]},"h":1,"t":4,"s":[0.20421302444736467]},{"i":{"x":[0],"y":[0]},"o":{"x":[1],"y":[1]},"h":1,"t":5,"s":[0.8908846918708793]},{"i":{"x":[0],"y":[0]},"o":{"x":[1],"y":[1]},"h":1,"t":6,"s":[2.21322192707766]},{"i":{"x":[0],"y":[0]},"o":{"x":[1],"y":[1]},"h":1,"t":7,"s":[4.418489554435204]},{"i":{"x":[0],"y":[0]},"o":{"x":[1],"y":[1]},"h":1,"t":8,"s":[7.9490449733617154]},{"i":{"x":[0],"y":[0]},"o":{"x":[1],"y":[1]},"h":1,"t":9,"s":[13.733638806968115]},{"i":{"x":[0],"y":[0]},"o":{"x":[1],"y":[1]},"h":1,"t":10,"s":[24.35423892026852]},{"i":{"x":[0],"y":[0]},"o":{"x":[1],"y":[1]},"h":1,"t":11,"s":[50]},{"i":{"x":[0],"y":[0]},"o":{"x":[1],"y":[1]},"h":1,"t":12,"s":[75.64576107973147]},{"i":{"x":[0],"y":[0]},"o":{"x":[1],"y":[1]},"h":1,"t":13,"s":[86.2663611930319]},{"i":{"x":[0],"y":[0]},"o":{"x":[1],"y":[1]},"h":1,"t":14,"s":[92.05095502663828]},{"i":{"x":[0],"y":[0]},"o":{"x":[1],"y":[1]},"h":1,"t":15,"s":[95.5815104455648]},{"i":{"x":[0],"y":[0]},"o":{"x":[1],"y":[1]},"h":1,"t":16,"s":[97.78677807292233]},{"i":{"x":[0],"y":[0]},"o":{"x":[1],"y":[1]},"h":1,"t":17,"s":[99.10911530812913]},{"i":{"x":[0],"y":[0]},"o":{"x":[1],"y":[1]},"h":1,"t":18,"s":[99.79578697555264]},{"i":{"x":[0],"y":[0]},"o":{"x":[1],"y":[1]},"h":1,"t":19,"s":[100]},{"i":{"x":[0],"y":[0]},"o":{"x":[1],"y":[1]},"h":1,"t":20,"s":[100]},{"i":{"x":[0],"y":[0]},"o":{"x":[1],"y":[1]},"h":1,"t":21,"s":[100]},{"i":{"x":[0],"y":[0]},"o":{"x":[1],"y":[1]},"h":1,"t":22,"s":[100]},{"i":{"x":[0],"y":[0]},"o":{"x":[1],"y":[1]},"h":1,"t":23,"s":[100]},{"i":{"x":[0],"y":[0]},"o":{"x":[1],"y":[1]},"h":1,"t":24,"s":[100]},{"i":{"x":[0],"y":[0]},"o":{"x":[1],"y":[1]},"h":1,"t":25,"s":[100]},{"i":{"x":[0],"y":[0]},"o":{"x":[1],"y":[1]},"h":1,"t":26,"s":[100]},{"i":{"x":[0],"y":[0]},"o":{"x":[1],"y":[1]},"h":1,"t":27,"s":[100]},{"i":{"x":[0],"y":[0]},"o":{"x":[1],"y":[1]},"h":1,"t":28,"s":[100]},{"i":{"x":[0],"y":[0]},"o":{"x":[1],"y":[1]},"h":1,"t":29,"s":[100]},{"i":{"x":[0],"y":[0]},"o":{"x":[1],"y":[1]},"h":1,"t":30,"s":[100]},{"i":{"x":[0],"y":[0]},"o":{"x":[1],"y":[1]},"h":1,"t":31,"s":[100]},{"i":{"x":[0],"y":[0]},"o":{"x":[1],"y":[1]},"h":1,"t":32,"s":[99.81996951841349]},{"i":{"x":[0],"y":[0]},"o":{"x":[1],"y":[1]},"h":1,"t":33,"s":[99.21930195991678]},{"i":{"x":[0],"y":[0]},"o":{"x":[1],"y":[1]},"h":1,"t":34,"s":[98.07552789183043]},{"i":{"x":[0],"y":[0]},"o":{"x":[1],"y":[1]},"h":1,"t":35,"s":[96.1985180370635]},{"i":{"x":[0],"y":[0]},"o":{"x":[1],"y":[1]},"h":1,"t":36,"s":[93.26690563755626]},{"i":{"x":[0],"y":[0]},"o":{"x":[1],"y":[1]},"h":1,"t":37,"s":[88.6645929534551]},{"i":{"x":[0],"y":[0]},"o":{"x":[1],"y":[1]},"h":1,"t":38,"s":[80.94133940622638]},{"i":{"x":[0],"y":[0]},"o":{"x":[1],"y":[1]},"h":1,"t":39,"s":[65.18642797601737]},{"i":{"x":[0],"y":[0]},"o":{"x":[1],"y":[1]},"h":1,"t":40,"s":[34.81357202398262]},{"i":{"x":[0],"y":[0]},"o":{"x":[1],"y":[1]},"h":1,"t":41,"s":[19.05866059377366]},{"i":{"x":[0],"y":[0]},"o":{"x":[1],"y":[1]},"h":1,"t":42,"s":[11.335407046544887]},{"i":{"x":[0],"y":[0]},"o":{"x":[1],"y":[1]},"h":1,"t":43,"s":[6.733094362443737]},{"i":{"x":[0],"y":[0]},"o":{"x":[1],"y":[1]},"h":1,"t":44,"s":[3.8014819629364927]},{"i":{"x":[0],"y":[0]},"o":{"x":[1],"y":[1]},"h":1,"t":45,"s":[1.9244721081695615]},{"i":{"x":[0],"y":[0]},"o":{"x":[1],"y":[1]},"h":1,"t":46,"s":[0.7806980400832275]},{"i":{"x":[0],"y":[0]},"o":{"x":[1],"y":[1]},"h":1,"t":47,"s":[0.1800304815865128]},{"i":{"x":[0],"y":[0]},"o":{"x":[1],"y":[1]},"h":1,"t":48,"s":[0]},{"i":{"x":[0],"y":[0]},"o":{"x":[1],"y":[1]},"h":1,"t":49,"s":[0]},{"i":{"x":[0],"y":[0]},"o":{"x":[1],"y":[1]},"h":1,"t":50,"s":[0]},{"i":{"x":[0],"y":[0]},"o":{"x":[1],"y":[1]},"h":1,"t":51,"s":[0]},{"i":{"x":[0],"y":[0]},"o":{"x":[1],"y":[1]},"h":1,"t":52,"s":[0]},{"i":{"x":[0],"y":[0]},"o":{"x":[1],"y":[1]},"h":1,"t":53,"s":[0]},{"i":{"x":[0],"y":[0]},"o":{"x":[1],"y":[1]},"h":1,"t":54,"s":[0]},{"i":{"x":[0],"y":[0]},"o":{"x":[1],"y":[1]},"h":1,"t":55,"s":[0]},{"i":{"x":[0],"y":[0]},"o":{"x":[1],"y":[1]},"h":1,"t":56,"s":[0]},{"i":{"x":[0],"y":[0]},"o":{"x":[1],"y":[1]},"h":1,"t":57,"s":[0]},{"i":{"x":[0],"y":[0]},"o":{"x":[1],"y":[1]},"h":1,"t":58,"s":[0]},{"i":{"x":[0],"y":[0]},"o":{"x":[1],"y":[1]},"h":1,"t":59,"s":[0]}]},"r":{"a":0,"k":0},"p":{"a":0,"k":[-117.0322265625,0.001983642578125,0]},"a":{"a":0,"k":[0,0,0]},"s":{"a":0,"k":[100,100,100]},"sk":{"a":0,"k":0},"sa":{"a":0,"k":0}},"shapes":[{"ty":"gr","it":[{"ty":"sh","ks":{"a":0,"k":{"c":true,"v":[[3.6101413,-2.482536],[4.350429,-0.042333126],[3.0637536,3.064219],[-0.04218769,4.350281],[-2.4826996,3.6099958],[-4.100399,1.6391768],[-4.3504295,-0.8992007],[-3.14812,-3.1479692],[-0.8990402,-4.350281],[1.638722,-4.0999393]],"i":[[-0.48288829999999994,-0.7221845],[0,-0.8685185740000001],[0.8237275999999998,-0.8240370000000001],[1.16488219,0],[0.7224881000000001,0.4831972000000002],[0.3325615000000002,0.8022575999999999],[-0.1693511000000001,0.852570794],[-0.6145003999999998,0.6141909999999999],[-0.8522668,0.16996460000000013],[-0.80256086,-0.3328652999999999]],"o":[[0.48257920000000043,0.7221843000000001],[0,1.1651854259999999],[-0.8237333000000002,0.8231148999999998],[-0.86882781,0],[-0.7221843999999997,-0.4825792],[-0.33256149999999973,-0.8028702],[0.1696548,-0.8519575000000001],[0.6141911000000002,-0.6141911000000002],[0.851957776,-0.16934499999999986],[0.8025612,0.33225229999999994]]}}},{"ty":"fl","o":{"a":0,"k":100},"c":{"a":0,"k":[0.00392156862745098,0.054901960784313725,0.24313725490196078]}},{"ty":"rd","r":{"a":0,"k":0}},{"ty":"tr","o":{"a":0,"k":100},"r":{"a":0,"k":0},"p":{"a":0,"k":[0,0,0]},"a":{"a":0,"k":[0,0,0]},"s":{"a":0,"k":[100,100,100]}}]}],"ip":3,"op":60,"st":0,"bm":0,"nm":"Vector","parent":2,"hasMask":false},{"hd":false,"ty":4,"ddd":0,"ind":11,"sr":1,"ao":0,"ks":{"o":{"a":1,"k":[{"i":{"x":[0],"y":[0]},"o":{"x":[1],"y":[1]},"h":1,"t":0,"s":[0]},{"i":{"x":[0],"y":[0]},"o":{"x":[1],"y":[1]},"h":1,"t":1,"s":[0.20421302444736467]},{"i":{"x":[0],"y":[0]},"o":{"x":[1],"y":[1]},"h":1,"t":2,"s":[0.8908846918708793]},{"i":{"x":[0],"y":[0]},"o":{"x":[1],"y":[1]},"h":1,"t":3,"s":[2.21322192707766]},{"i":{"x":[0],"y":[0]},"o":{"x":[1],"y":[1]},"h":1,"t":4,"s":[4.418489554435204]},{"i":{"x":[0],"y":[0]},"o":{"x":[1],"y":[1]},"h":1,"t":5,"s":[7.9490449733617154]},{"i":{"x":[0],"y":[0]},"o":{"x":[1],"y":[1]},"h":1,"t":6,"s":[13.733638806968115]},{"i":{"x":[0],"y":[0]},"o":{"x":[1],"y":[1]},"h":1,"t":7,"s":[24.35423892026852]},{"i":{"x":[0],"y":[0]},"o":{"x":[1],"y":[1]},"h":1,"t":8,"s":[50]},{"i":{"x":[0],"y":[0]},"o":{"x":[1],"y":[1]},"h":1,"t":9,"s":[75.64576107973147]},{"i":{"x":[0],"y":[0]},"o":{"x":[1],"y":[1]},"h":1,"t":10,"s":[86.2663611930319]},{"i":{"x":[0],"y":[0]},"o":{"x":[1],"y":[1]},"h":1,"t":11,"s":[92.05095502663828]},{"i":{"x":[0],"y":[0]},"o":{"x":[1],"y":[1]},"h":1,"t":12,"s":[95.5815104455648]},{"i":{"x":[0],"y":[0]},"o":{"x":[1],"y":[1]},"h":1,"t":13,"s":[97.78677807292233]},{"i":{"x":[0],"y":[0]},"o":{"x":[1],"y":[1]},"h":1,"t":14,"s":[99.10911530812913]},{"i":{"x":[0],"y":[0]},"o":{"x":[1],"y":[1]},"h":1,"t":15,"s":[99.79578697555264]},{"i":{"x":[0],"y":[0]},"o":{"x":[1],"y":[1]},"h":1,"t":16,"s":[100]},{"i":{"x":[0],"y":[0]},"o":{"x":[1],"y":[1]},"h":1,"t":17,"s":[100]},{"i":{"x":[0],"y":[0]},"o":{"x":[1],"y":[1]},"h":1,"t":18,"s":[100]},{"i":{"x":[0],"y":[0]},"o":{"x":[1],"y":[1]},"h":1,"t":19,"s":[100]},{"i":{"x":[0],"y":[0]},"o":{"x":[1],"y":[1]},"h":1,"t":20,"s":[100]},{"i":{"x":[0],"y":[0]},"o":{"x":[1],"y":[1]},"h":1,"t":21,"s":[100]},{"i":{"x":[0],"y":[0]},"o":{"x":[1],"y":[1]},"h":1,"t":22,"s":[100]},{"i":{"x":[0],"y":[0]},"o":{"x":[1],"y":[1]},"h":1,"t":23,"s":[100]},{"i":{"x":[0],"y":[0]},"o":{"x":[1],"y":[1]},"h":1,"t":24,"s":[100]},{"i":{"x":[0],"y":[0]},"o":{"x":[1],"y":[1]},"h":1,"t":25,"s":[100]},{"i":{"x":[0],"y":[0]},"o":{"x":[1],"y":[1]},"h":1,"t":26,"s":[100]},{"i":{"x":[0],"y":[0]},"o":{"x":[1],"y":[1]},"h":1,"t":27,"s":[100]},{"i":{"x":[0],"y":[0]},"o":{"x":[1],"y":[1]},"h":1,"t":28,"s":[100]},{"i":{"x":[0],"y":[0]},"o":{"x":[1],"y":[1]},"h":1,"t":29,"s":[99.81996951841349]},{"i":{"x":[0],"y":[0]},"o":{"x":[1],"y":[1]},"h":1,"t":30,"s":[99.21930195991678]},{"i":{"x":[0],"y":[0]},"o":{"x":[1],"y":[1]},"h":1,"t":31,"s":[98.07552789183043]},{"i":{"x":[0],"y":[0]},"o":{"x":[1],"y":[1]},"h":1,"t":32,"s":[96.1985180370635]},{"i":{"x":[0],"y":[0]},"o":{"x":[1],"y":[1]},"h":1,"t":33,"s":[93.26690563755626]},{"i":{"x":[0],"y":[0]},"o":{"x":[1],"y":[1]},"h":1,"t":34,"s":[88.6645929534551]},{"i":{"x":[0],"y":[0]},"o":{"x":[1],"y":[1]},"h":1,"t":35,"s":[80.94133940622638]},{"i":{"x":[0],"y":[0]},"o":{"x":[1],"y":[1]},"h":1,"t":36,"s":[65.18642797601737]},{"i":{"x":[0],"y":[0]},"o":{"x":[1],"y":[1]},"h":1,"t":37,"s":[34.81357202398262]},{"i":{"x":[0],"y":[0]},"o":{"x":[1],"y":[1]},"h":1,"t":38,"s":[19.05866059377366]},{"i":{"x":[0],"y":[0]},"o":{"x":[1],"y":[1]},"h":1,"t":39,"s":[11.335407046544887]},{"i":{"x":[0],"y":[0]},"o":{"x":[1],"y":[1]},"h":1,"t":40,"s":[6.733094362443737]},{"i":{"x":[0],"y":[0]},"o":{"x":[1],"y":[1]},"h":1,"t":41,"s":[3.8014819629364927]},{"i":{"x":[0],"y":[0]},"o":{"x":[1],"y":[1]},"h":1,"t":42,"s":[1.9244721081695615]},{"i":{"x":[0],"y":[0]},"o":{"x":[1],"y":[1]},"h":1,"t":43,"s":[0.7806980400832275]},{"i":{"x":[0],"y":[0]},"o":{"x":[1],"y":[1]},"h":1,"t":44,"s":[0.1800304815865128]},{"i":{"x":[0],"y":[0]},"o":{"x":[1],"y":[1]},"h":1,"t":45,"s":[0]},{"i":{"x":[0],"y":[0]},"o":{"x":[1],"y":[1]},"h":1,"t":46,"s":[0]},{"i":{"x":[0],"y":[0]},"o":{"x":[1],"y":[1]},"h":1,"t":47,"s":[0]},{"i":{"x":[0],"y":[0]},"o":{"x":[1],"y":[1]},"h":1,"t":48,"s":[0]},{"i":{"x":[0],"y":[0]},"o":{"x":[1],"y":[1]},"h":1,"t":49,"s":[0]},{"i":{"x":[0],"y":[0]},"o":{"x":[1],"y":[1]},"h":1,"t":50,"s":[0]},{"i":{"x":[0],"y":[0]},"o":{"x":[1],"y":[1]},"h":1,"t":51,"s":[0]},{"i":{"x":[0],"y":[0]},"o":{"x":[1],"y":[1]},"h":1,"t":52,"s":[0]},{"i":{"x":[0],"y":[0]},"o":{"x":[1],"y":[1]},"h":1,"t":53,"s":[0]},{"i":{"x":[0],"y":[0]},"o":{"x":[1],"y":[1]},"h":1,"t":54,"s":[0]},{"i":{"x":[0],"y":[0]},"o":{"x":[1],"y":[1]},"h":1,"t":55,"s":[0]},{"i":{"x":[0],"y":[0]},"o":{"x":[1],"y":[1]},"h":1,"t":56,"s":[0]},{"i":{"x":[0],"y":[0]},"o":{"x":[1],"y":[1]},"h":1,"t":57,"s":[0]},{"i":{"x":[0],"y":[0]},"o":{"x":[1],"y":[1]},"h":1,"t":58,"s":[0]},{"i":{"x":[0],"y":[0]},"o":{"x":[1],"y":[1]},"h":1,"t":59,"s":[0]}]},"r":{"a":0,"k":0},"p":{"a":0,"k":[-117.0322265625,22.23199462890625,0]},"a":{"a":0,"k":[0,0,0]},"s":{"a":0,"k":[99.99999403953552,99.99999403953552,100]},"sk":{"a":0,"k":0},"sa":{"a":0,"k":0}},"shapes":[{"ty":"gr","it":[{"ty":"sh","ks":{"a":0,"k":{"c":true,"v":[[3.6101413,-2.4825344],[4.350429,-0.04233122],[3.0637536,3.064219],[-0.04218769,4.350281],[-2.4826996,3.609993],[-4.100399,1.6391788],[-4.3504295,-0.8992009],[-3.14812,-3.1479673],[-0.8990402,-4.3502812],[1.638722,-4.0999374]],"i":[[-0.48288829999999994,-0.7221844000000002],[0,-0.86851883],[0.8237275999999998,-0.8240370000000001],[1.16488219,0],[0.7224881000000001,0.48319800000000024],[0.3325615000000002,0.8022574999999998],[-0.1693511000000001,0.852570517],[-0.6145003999999998,0.6141909999999999],[-0.8522668,0.1699642000000008],[-0.80256086,-0.3328652999999999]],"o":[[0.48257920000000043,0.7221844],[0,1.1651854199999998],[-0.8237333000000002,0.8231148999999998],[-0.86882781,0],[-0.7221843999999997,-0.48257879999999975],[-0.33256149999999973,-0.8028703],[0.1696548,-0.8519576000000001],[0.6141911000000002,-0.6141911000000002],[0.851957776,-0.1693453999999992],[0.8025612,0.3322522000000001]]}}},{"ty":"fl","o":{"a":0,"k":100},"c":{"a":0,"k":[0.00392156862745098,0.054901960784313725,0.24313725490196078]}},{"ty":"rd","r":{"a":0,"k":0}},{"ty":"tr","o":{"a":0,"k":100},"r":{"a":0,"k":0},"p":{"a":0,"k":[0,0,0]},"a":{"a":0,"k":[0,0,0]},"s":{"a":0,"k":[100,100,100]}}]}],"ip":0,"op":60,"st":0,"bm":0,"nm":"Vector","parent":2,"hasMask":false}],"ip":0,"op":60}